torchac/__init__.py
torchac/torchac.py
torchac/backend/torchac_backend.cpp
torchac-0.9.3.dist-info/LICENSE.txt
torchac-0.9.3.dist-info/METADATA
torchac-0.9.3.dist-info/WHEEL
torchac-0.9.3.dist-info/top_level.txt
torchac-0.9.3.dist-info/RECORD
