Metadata-Version: 2.1
Name: torchac
Version: 0.9.3
Summary: Fast Arithmetic Coding for PyTorch
Home-page: https://github.com/fab-jul/torchac
Author: fab-jul
Author-email: fabianjul@gmail.com
License: GNU General Public License
Platform: UNKNOWN
Requires-Python: >=3.6
